workspace_extractor/__init__.py
workspace_extractor/manager.py
workspace_extractor/mapping.py
workspace_extractor/sizing.py
workspace_extractor/exceptions/__init__.py
workspace_extractor/exceptions/no_cluster_events_error.py
workspace_extractor/utils/__init__.py
workspace_extractor/utils/util.py
workspace_extractor/utils/util_file.py
workspace_extractor-0.0.1.dist-info/licenses/LICENSE
workspace_extractor-0.0.1.dist-info/METADATA
workspace_extractor-0.0.1.dist-info/WHEEL
workspace_extractor-0.0.1.dist-info/top_level.txt
workspace_extractor-0.0.1.dist-info/RECORD
