Metadata-Version: 2.4
Name: workspace-extractor
Version: 0.0.1
Summary: Workspace estimator
Author-email: Snowflake <erick.cuberojimenez@snowflake.com>
Project-URL: Homepage, https://github.com/Snowflake-Labs/Workspace-Estimator
Project-URL: Bug Tracker, https://github.com/Snowflake-Labs/Workspace-Estimator/issues
Project-URL: Documentation, https://github.com/Snowflake-Labs/Workspace-Estimator/blob/main/README.md
Keywords: workspace extractor,we
Classifier: Development Status :: 4 - Beta
Classifier: Intended Audience :: Developers
Classifier: License :: OSI Approved :: Apache Software License
Classifier: Programming Language :: Python :: 3
Classifier: Programming Language :: Python :: 3.10
Classifier: Programming Language :: Python :: 3.11
Classifier: Programming Language :: Python :: 3.12
Classifier: Operating System :: OS Independent
Classifier: Topic :: Software Development :: Libraries :: Python Modules
Classifier: Topic :: Utilities
Requires-Python: >=3.10
License-File: LICENSE
Requires-Dist: tqdm
Requires-Dist: requests
Requires-Dist: pandas
Dynamic: license-file
